pcg_springer_features/__init__.py
pcg_springer_features/schmidt_heart_rate.py
pcg_springer_features/schmidt_spike_removal.py
pcg_springer_features/springer_dwt.py
pcg_springer_features/springer_features.py
pcg_springer_features/version.py
pcg_springer_features-0.3.dist-info/LICENSE
pcg_springer_features-0.3.dist-info/METADATA
pcg_springer_features-0.3.dist-info/WHEEL
pcg_springer_features-0.3.dist-info/top_level.txt
pcg_springer_features-0.3.dist-info/RECORD
